{
  "scan_id": 46,
  "target": "heraldcollege.edu.np",
  "endpoints": [
    {
      "url": "https://bizcorecommunity.heraldcollege.edu.np/",
      "status_code": 200,
      "content_length": -1,
      "title": "Biz Core Community",
      "headers": {
        "CF-RAY": "9c57a1a33f2c8e54-KTM",
        "Content-Type": "text/html; charset=UTF-8",
        "Server": "cloudflare"
      },
      "fingerprints": [
        "cloudflare",
        "html",
        "2xx"
      ],
      "evidence": {
        "2xx": "status=200",
        "cloudflare": "Header=CF-RAY",
        "html": "Content-Type=text/html; charset=UTF-8"
      }
    },
    {
      "url": "http://bizcorecommunity.heraldcollege.edu.np/",
      "status_code": 200,
      "content_length": -1,
      "title": "Biz Core Community",
      "headers": {
        "CF-RAY": "9c57a1a33f2a8e54-KTM",
        "Content-Type": "text/html; charset=UTF-8",
        "Server": "cloudflare"
      },
      "fingerprints": [
        "cloudflare",
        "html",
        "2xx"
      ],
      "evidence": {
        "2xx": "status=200",
        "cloudflare": "Header=CF-RAY",
        "html": "Content-Type=text/html; charset=UTF-8"
      }
    },
    {
      "url": "http://heraldcollege.edu.np/login",
      "status_code": 200,
      "content_length": -1,
      "title": "",
      "headers": {
        "CF-RAY": "9c57a1af3f1dfde4-SIN",
        "Content-Type": "text/html; charset=UTF-8",
        "Server": "cloudflare",
        "Set-Cookie": "XSRF-TOKEN=eyJpdiI6IldaN0RJL2dsVjQyU0tHT3BwS1lxaVE9PSIsInZhbHVlIjoiaHhBbm5IOFE1dFg3OU5QQk1IeFBiK2dZbDlHbmpFaUxTWENZa2luOGREV3RyQVBRekYyRWF3elpLV1RQQ09RMkhQVVVxQ0FITGtOZk05VnpCL05He"
      },
      "fingerprints": [
        "cloudflare",
        "html",
        "2xx"
      ],
      "evidence": {
        "2xx": "status=200",
        "cloudflare": "Header=CF-RAY",
        "html": "Content-Type=text/html; charset=UTF-8"
      }
    },
    {
      "url": "http://heraldcollege.edu.np/",
      "status_code": 200,
      "content_length": -1,
      "title": "UK University Degree in Nepal | UK Degree in Kathmandu",
      "headers": {
        "CF-RAY": "9c57a1af3f1cfde4-SIN",
        "Content-Type": "text/html; charset=UTF-8",
        "Server": "cloudflare",
        "Set-Cookie": "XSRF-TOKEN=eyJpdiI6IjVLN0IwTDRKaUJJRjM0NC9BTi85NFE9PSIsInZhbHVlIjoiSjJKK0tuWk9DeFd3ZnhGZTVUUXVsdFdQaVUyWXpHMHhDaHJPMHBkVGdyT0FXWHJKdzNJWEFZQWNPeE5QRWN5T05zQWRjU1VRekZCa28xeWorS0xpO"
      },
      "fingerprints": [
        "cloudflare",
        "html",
        "2xx"
      ],
      "evidence": {
        "2xx": "status=200",
        "cloudflare": "Header=CF-RAY",
        "html": "Content-Type=text/html; charset=UTF-8"
      }
    },
    {
      "url": "https://heraldcollege.edu.np/",
      "status_code": 200,
      "content_length": -1,
      "title": "UK University Degree in Nepal | UK Degree in Kathmandu",
      "headers": {
        "CF-RAY": "9c57a1b5fa61fde4-SIN",
        "Content-Type": "text/html; charset=UTF-8",
        "Server": "cloudflare",
        "Set-Cookie": "XSRF-TOKEN=eyJpdiI6InppYUt2QjhubFFPZDUzaFZqYUhqUFE9PSIsInZhbHVlIjoiWm00Wk9vSjZDb2QxdGFmTlRISGJ2WmxobHZTVnFYUkZVTUhXRy8wREtmTUdaRVRlekhsTUw5RjAyZ0hGeHNUdThmNFNmblZzWjZBZG4zdXc3L09Nd"
      },
      "fingerprints": [
        "cloudflare",
        "html",
        "2xx"
      ],
      "evidence": {
        "2xx": "status=200",
        "cloudflare": "Header=CF-RAY",
        "html": "Content-Type=text/html; charset=UTF-8"
      }
    },
    {
      "url": "https://heraldcollege.edu.np/login",
      "status_code": 200,
      "content_length": -1,
      "title": "",
      "headers": {
        "CF-RAY": "9c57a1b69bc8fde4-SIN",
        "Content-Type": "text/html; charset=UTF-8",
        "Server": "cloudflare",
        "Set-Cookie": "XSRF-TOKEN=eyJpdiI6IlQ2MURDVW1jWXZMNGhudHh2R0tDM3c9PSIsInZhbHVlIjoic1JDbUpYQmRqSG1WeXpaR0JwYm1xQ0dEQm43aU9kblNXN3loeVE1Sk5DQTh2Rm9ybGljMU5VQUwwYUN6eUNoVE8xOUhIYVF5MXFOOWlJTG5XbE1pN"
      },
      "fingerprints": [
        "cloudflare",
        "html",
        "2xx"
      ],
      "evidence": {
        "2xx": "status=200",
        "cloudflare": "Header=CF-RAY",
        "html": "Content-Type=text/html; charset=UTF-8"
      }
    },
    {
      "url": "http://portal.heraldcollege.edu.np/",
      "status_code": 200,
      "content_length": -1,
      "title": "Herald College Server",
      "headers": {
        "CF-RAY": "9c57a1c07ed58e57-KTM",
        "Content-Type": "text/html; charset=utf-8",
        "Server": "cloudflare"
      },
      "fingerprints": [
        "cloudflare",
        "html",
        "2xx"
      ],
      "evidence": {
        "2xx": "status=200",
        "cloudflare": "Header=CF-RAY",
        "html": "Content-Type=text/html; charset=utf-8"
      }
    },
    {
      "url": "https://portal.heraldcollege.edu.np/",
      "status_code": 200,
      "content_length": -1,
      "title": "Herald College Server",
      "headers": {
        "CF-RAY": "9c57a1c74e678e57-KTM",
        "Content-Type": "text/html; charset=utf-8",
        "Server": "cloudflare"
      },
      "fingerprints": [
        "cloudflare",
        "html",
        "2xx"
      ],
      "evidence": {
        "2xx": "status=200",
        "cloudflare": "Header=CF-RAY",
        "html": "Content-Type=text/html; charset=utf-8"
      }
    },
    {
      "url": "http://creators.heraldcollege.edu.np/",
      "status_code": 200,
      "content_length": -1,
      "title": "Creators Community",
      "headers": {
        "CF-RAY": "9c57a1d2ec4adfe3-SIN",
        "Content-Type": "text/html; charset=utf-8",
        "Server": "cloudflare"
      },
      "fingerprints": [
        "cloudflare",
        "html",
        "2xx"
      ],
      "evidence": {
        "2xx": "status=200",
        "cloudflare": "Header=CF-RAY",
        "html": "Content-Type=text/html; charset=utf-8"
      }
    },
    {
      "url": "https://creators.heraldcollege.edu.np/",
      "status_code": 200,
      "content_length": -1,
      "title": "Creators Community",
      "headers": {
        "CF-RAY": "9c57a1d8f89bdfe3-SIN",
        "Content-Type": "text/html; charset=utf-8",
        "Server": "cloudflare"
      },
      "fingerprints": [
        "cloudflare",
        "html",
        "2xx"
      ],
      "evidence": {
        "2xx": "status=200",
        "cloudflare": "Header=CF-RAY",
        "html": "Content-Type=text/html; charset=utf-8"
      }
    },
    {
      "url": "http://www.heraldcollege.edu.np/login",
      "status_code": 200,
      "content_length": -1,
      "title": "",
      "headers": {
        "CF-RAY": "9c57a1e56d1afde4-SIN",
        "Content-Type": "text/html; charset=UTF-8",
        "Server": "cloudflare",
        "Set-Cookie": "XSRF-TOKEN=eyJpdiI6IlNQaWIwK04rMi82cTVKNi92ZUFSMlE9PSIsInZhbHVlIjoiRWQ3TUwxV3VLNTBkeUYzVDVjc2hCQm4wemRxYjJ4cVNkL0pmMHBSUWtld2ZjdXo3WTNBaTdXYmJMSHc4TS95OG9LbzJqRDJLTWtaZmI1K0tIckp0U"
      },
      "fingerprints": [
        "cloudflare",
        "html",
        "2xx"
      ],
      "evidence": {
        "2xx": "status=200",
        "cloudflare": "Header=CF-RAY",
        "html": "Content-Type=text/html; charset=UTF-8"
      }
    },
    {
      "url": "http://www.heraldcollege.edu.np/",
      "status_code": 200,
      "content_length": -1,
      "title": "UK University Degree in Nepal | UK Degree in Kathmandu",
      "headers": {
        "CF-RAY": "9c57a1e57d1efde4-SIN",
        "Content-Type": "text/html; charset=UTF-8",
        "Server": "cloudflare",
        "Set-Cookie": "XSRF-TOKEN=eyJpdiI6Im04U0ZrRTdMV2lBRkNneFlSVXlWOVE9PSIsInZhbHVlIjoiaERaOGZLTHAyeExST1Y5ZHhheHNUVmE0TXl0VHI5SnREQjhZWUswbXF0aFp0UDRTbS9KakJYbll3c1orbEJSWTJndnlERmcxdU85TjFHc0RGVzJGL"
      },
      "fingerprints": [
        "cloudflare",
        "html",
        "2xx"
      ],
      "evidence": {
        "2xx": "status=200",
        "cloudflare": "Header=CF-RAY",
        "html": "Content-Type=text/html; charset=UTF-8"
      }
    },
    {
      "url": "https://www.heraldcollege.edu.np/login",
      "status_code": 200,
      "content_length": -1,
      "title": "",
      "headers": {
        "CF-RAY": "9c57a1eb9bf3fde4-SIN",
        "Content-Type": "text/html; charset=UTF-8",
        "Server": "cloudflare",
        "Set-Cookie": "XSRF-TOKEN=eyJpdiI6IlZZc1NpR2trQzdhN096VzAxWjhnQXc9PSIsInZhbHVlIjoianU1d0l0aFlYd0lKZXh0RmxFUDlJaTJZQ1E0VlltZE1tL0JPN1grZWRVV2ZJTEJIVlVnUi9qWVlIejcyOFJQVEFhMWh2Y2ZXWDg3c2ZNc3BLUHp1d"
      },
      "fingerprints": [
        "cloudflare",
        "html",
        "2xx"
      ],
      "evidence": {
        "2xx": "status=200",
        "cloudflare": "Header=CF-RAY",
        "html": "Content-Type=text/html; charset=UTF-8"
      }
    },
    {
      "url": "https://www.heraldcollege.edu.np/",
      "status_code": 200,
      "content_length": -1,
      "title": "UK University Degree in Nepal | UK Degree in Kathmandu",
      "headers": {
        "CF-RAY": "9c57a1eb7bbefde4-SIN",
        "Content-Type": "text/html; charset=UTF-8",
        "Server": "cloudflare",
        "Set-Cookie": "XSRF-TOKEN=eyJpdiI6Im5HZHRoV3lwQ25PeVNjbEEyTG1NVmc9PSIsInZhbHVlIjoiUSsrTWR4Wkl3Skhsd0ZwNHJKV1VOYk5CWHF1Z3dPVDU4b1piRk9oVUJHT1Q0ME9SNnNXNVJaYnRFN1Y3VTViWFpsVDl1ZkRGUkluZ2xGYWREaVRsc"
      },
      "fingerprints": [
        "cloudflare",
        "html",
        "2xx"
      ],
      "evidence": {
        "2xx": "status=200",
        "cloudflare": "Header=CF-RAY",
        "html": "Content-Type=text/html; charset=UTF-8"
      }
    },
    {
      "url": "http://iotinnovatorscommunity.heraldcollege.edu.np/",
      "status_code": 200,
      "content_length": -1,
      "title": "Index of /",
      "headers": {
        "CF-RAY": "9c57a1f5fb468e51-KTM",
        "Content-Type": "text/html",
        "Server": "cloudflare"
      },
      "fingerprints": [
        "cloudflare",
        "html",
        "2xx"
      ],
      "evidence": {
        "2xx": "status=200",
        "cloudflare": "Header=CF-RAY",
        "html": "Content-Type=text/html"
      }
    },
    {
      "url": "http://admission.heraldcollege.edu.np/",
      "status_code": 200,
      "content_length": 4831,
      "title": "Student Enrollment",
      "headers": {
        "Content-Type": "text/html",
        "Server": "Caddy"
      },
      "fingerprints": [
        "html",
        "2xx"
      ],
      "evidence": {
        "2xx": "status=200",
        "html": "Content-Type=text/html"
      }
    },
    {
      "url": "https://iotinnovatorscommunity.heraldcollege.edu.np/",
      "status_code": 200,
      "content_length": -1,
      "title": "Index of /",
      "headers": {
        "CF-RAY": "9c57a1fbc8d88e51-KTM",
        "Content-Type": "text/html",
        "Server": "cloudflare"
      },
      "fingerprints": [
        "cloudflare",
        "html",
        "2xx"
      ],
      "evidence": {
        "2xx": "status=200",
        "cloudflare": "Header=CF-RAY",
        "html": "Content-Type=text/html"
      }
    },
    {
      "url": "https://admission.heraldcollege.edu.np/",
      "status_code": 200,
      "content_length": 4831,
      "title": "Student Enrollment",
      "headers": {
        "Content-Type": "text/html",
        "Server": "Caddy"
      },
      "fingerprints": [
        "html",
        "2xx"
      ],
      "evidence": {
        "2xx": "status=200",
        "html": "Content-Type=text/html"
      }
    },
    {
      "url": "http://ethicalcommunity.heraldcollege.edu.np/",
      "status_code": 200,
      "content_length": -1,
      "title": "Ethical HCK",
      "headers": {
        "CF-RAY": "9c57a2551d908e56-KTM",
        "Content-Type": "text/html; charset=UTF-8",
        "Server": "cloudflare"
      },
      "fingerprints": [
        "cloudflare",
        "html",
        "2xx"
      ],
      "evidence": {
        "2xx": "status=200",
        "cloudflare": "Header=CF-RAY",
        "html": "Content-Type=text/html; charset=UTF-8"
      }
    },
    {
      "url": "https://ethicalcommunity.heraldcollege.edu.np/",
      "status_code": 200,
      "content_length": -1,
      "title": "Ethical HCK",
      "headers": {
        "CF-RAY": "9c57a25b6bb88e56-KTM",
        "Content-Type": "text/html; charset=UTF-8",
        "Server": "cloudflare"
      },
      "fingerprints": [
        "cloudflare",
        "html",
        "2xx"
      ],
      "evidence": {
        "2xx": "status=200",
        "cloudflare": "Header=CF-RAY",
        "html": "Content-Type=text/html; charset=UTF-8"
      }
    },
    {
      "url": "http://gamedevheroes.heraldcollege.edu.np/",
      "status_code": 200,
      "content_length": -1,
      "title": "Game Dev Heros Community",
      "headers": {
        "CF-RAY": "9c57a2677ccffd1f-SIN",
        "Content-Type": "text/html; charset=UTF-8",
        "Server": "cloudflare"
      },
      "fingerprints": [
        "cloudflare",
        "html",
        "2xx"
      ],
      "evidence": {
        "2xx": "status=200",
        "cloudflare": "Header=CF-RAY",
        "html": "Content-Type=text/html; charset=UTF-8"
      }
    },
    {
      "url": "https://gamedevheroes.heraldcollege.edu.np/",
      "status_code": 200,
      "content_length": -1,
      "title": "Game Dev Heros Community",
      "headers": {
        "CF-RAY": "9c57a26d2b1bfd1f-SIN",
        "Content-Type": "text/html; charset=UTF-8",
        "Server": "cloudflare"
      },
      "fingerprints": [
        "cloudflare",
        "html",
        "2xx"
      ],
      "evidence": {
        "2xx": "status=200",
        "cloudflare": "Header=CF-RAY",
        "html": "Content-Type=text/html; charset=UTF-8"
      }
    },
    {
      "url": "http://events.heraldcollege.edu.np/",
      "status_code": 200,
      "content_length": -1,
      "title": "Calendar Application",
      "headers": {
        "CF-RAY": "9c57a29c2d898e51-KTM",
        "Content-Type": "text/html; charset=utf-8",
        "Server": "cloudflare",
        "X-Powered-By": "Next.js"
      },
      "fingerprints": [
        "cloudflare",
        "html",
        "2xx"
      ],
      "evidence": {
        "2xx": "status=200",
        "cloudflare": "Header=CF-RAY",
        "html": "Content-Type=text/html; charset=utf-8"
      }
    },
    {
      "url": "https://events.heraldcollege.edu.np/",
      "status_code": 200,
      "content_length": -1,
      "title": "Calendar Application",
      "headers": {
        "CF-RAY": "9c57a2a23c0d8e51-KTM",
        "Content-Type": "text/html; charset=utf-8",
        "Server": "cloudflare",
        "X-Powered-By": "Next.js"
      },
      "fingerprints": [
        "cloudflare",
        "html",
        "2xx"
      ],
      "evidence": {
        "2xx": "status=200",
        "cloudflare": "Header=CF-RAY",
        "html": "Content-Type=text/html; charset=utf-8"
      }
    },
    {
      "url": "http://showcase.heraldcollege.edu.np/",
      "status_code": 200,
      "content_length": -1,
      "title": "Herald College - Showcase Your Innovation",
      "headers": {
        "Content-Type": "text/html; charset=utf-8",
        "Server": "nginx/1.24.0 (Ubuntu)",
        "X-Powered-By": "Next.js"
      },
      "fingerprints": [
        "nginx",
        "html",
        "2xx"
      ],
      "evidence": {
        "2xx": "status=200",
        "html": "Content-Type=text/html; charset=utf-8",
        "nginx": "Server=nginx/1.24.0 (Ubuntu)"
      }
    },
    {
      "url": "https://showcase.heraldcollege.edu.np/",
      "status_code": 200,
      "content_length": -1,
      "title": "Herald College - Showcase Your Innovation",
      "headers": {
        "Content-Type": "text/html; charset=utf-8",
        "Server": "nginx/1.24.0 (Ubuntu)",
        "X-Powered-By": "Next.js"
      },
      "fingerprints": [
        "nginx",
        "html",
        "2xx"
      ],
      "evidence": {
        "2xx": "status=200",
        "html": "Content-Type=text/html; charset=utf-8",
        "nginx": "Server=nginx/1.24.0 (Ubuntu)"
      }
    },
    {
      "url": "http://attendance.heraldcollege.edu.np/",
      "status_code": 200,
      "content_length": 39380,
      "title": "Loading - AttendEase",
      "headers": {
        "Content-Type": "text/html",
        "Server": "Caddy"
      },
      "fingerprints": [
        "html",
        "2xx"
      ],
      "evidence": {
        "2xx": "status=200",
        "html": "Content-Type=text/html"
      }
    },
    {
      "url": "https://attendance.heraldcollege.edu.np/",
      "status_code": 200,
      "content_length": 39380,
      "title": "Loading - AttendEase",
      "headers": {
        "Content-Type": "text/html",
        "Server": "Caddy"
      },
      "fingerprints": [
        "html",
        "2xx"
      ],
      "evidence": {
        "2xx": "status=200",
        "html": "Content-Type=text/html"
      }
    },
    {
      "url": "http://creatorscommunity.heraldcollege.edu.np/",
      "status_code": 200,
      "content_length": -1,
      "title": "Creators Community",
      "headers": {
        "CF-RAY": "9c57a2f2ca2b5fab-SIN",
        "Content-Type": "text/html; charset=UTF-8",
        "Server": "cloudflare"
      },
      "fingerprints": [
        "cloudflare",
        "html",
        "2xx"
      ],
      "evidence": {
        "2xx": "status=200",
        "cloudflare": "Header=CF-RAY",
        "html": "Content-Type=text/html; charset=UTF-8"
      }
    },
    {
      "url": "https://creatorscommunity.heraldcollege.edu.np/",
      "status_code": 200,
      "content_length": -1,
      "title": "Creators Community",
      "headers": {
        "CF-RAY": "9c57a2f91fb85fab-SIN",
        "Content-Type": "text/html; charset=UTF-8",
        "Server": "cloudflare"
      },
      "fingerprints": [
        "cloudflare",
        "html",
        "2xx"
      ],
      "evidence": {
        "2xx": "status=200",
        "cloudflare": "Header=CF-RAY",
        "html": "Content-Type=text/html; charset=UTF-8"
      }
    }
  ],
  "saved_at": "2026-01-29T09:17:28.79424095Z"
}
