{
  "scan_id": 127,
  "target": "10.21.0.53",
  "endpoints": [
    {
      "url": "http://localhost/",
      "status_code": 200,
      "content_length": 896,
      "title": "Welcome to nginx!",
      "headers": {
        "Content-Type": "text/html",
        "Server": "nginx/1.30.1"
      },
      "fingerprints": [
        "Nginx:1.30.1"
      ],
      "evidence": {}
    },
    {
      "url": "http://10.21.0.53/",
      "status_code": 200,
      "content_length": 891,
      "title": "Metasploitable2 - Linux",
      "headers": {
        "Content-Type": "text/html",
        "Server": "Apache/2.2.8 (Ubuntu) DAV/2"
      },
      "fingerprints": [
        "Apache HTTP Server:2.2.8",
        "PHP:5.2.4",
        "Ubuntu",
        "mod_dav:2"
      ],
      "evidence": {}
    }
  ],
  "saved_at": "2026-05-28T03:59:41.882567655Z"
}
